{
  "data": {
    "pageNum": 1,
    "pageSize": 200,
    "totalPage": 1,
    "total": 3,
    "list": [
      {
        "product": {
          "id": 2557,
          "partnerId": 0,
          "brandId": 1,
          "productCategoryId": 3,
          "productAttributeCategoryId": 12,
          "name": "飞科鼻毛修剪器FS5605",
          "pic": "https://pic.flyco.net.cn/mall/goods/FS5605/main/FS5605-顺丰_1662357130960.jpg",
          "picWap": "https://pic.flyco.net.cn/mall/goods/FS5605/main/白底图_1662357141123.png",
          "productSn": "FS5605",
          "newStatus": "0",
          "recommandStatus": "0",
          "hotStatus": "0",
          "sort": 0,
          "sale": 0,
          "price": 69,
          "promotionPrice": 69,
          "subTitle": "飞科鼻毛修剪器男女用鼻毛剪鼻孔清洁器电动修剃鼻毛修剪刀充电式",
          "description": "立体拱形刀头 ",
          "unit": "",
          "weight": 0,
          "previewStatus": "0",
          "serviceIds": "",
          "keywords": "",
          "note": "",
          "detailTitle": "",
          "brandName": "飞科",
          "productCategoryName": "鼻毛修剪器",
          "spu": "",
          "color": "黑色",
          "createTime": "2022-09-05 13:51:48",
          "albumPics": "",
          "detailDesc": "",
          "detailHtml": "<img src=\"https://pic.flyco.net.cn/mall/goods/FS5605/info/FS5605鼻毛修剪器790 (1)_1662357061635.jpg\" /><img src=\"https://pic.flyco.net.cn/mall/goods/FS5605/info/FS5605鼻毛修剪器790 (2)_1662357061787.jpg\" /><img src=\"https://pic.flyco.net.cn/mall/goods/FS5605/info/FS5605鼻毛修剪器790 (3)_1662357063499.jpg\" /><img src=\"https://pic.flyco.net.cn/mall/goods/FS5605/info/FS5605鼻毛修剪器790 (4)_1662357063948.jpg\" /><img src=\"https://pic.flyco.net.cn/mall/goods/FS5605/info/FS5605鼻毛修剪器790 (5)_1662357066471.jpg\" /><img src=\"https://pic.flyco.net.cn/mall/goods/FS5605/info/FS5605鼻毛修剪器790 (6)_1662357068148.jpg\" /><img src=\"https://pic.flyco.net.cn/mall/goods/FS5605/info/FS5605鼻毛修剪器790 (7)_1662357071397.jpg\" /><img src=\"https://pic.flyco.net.cn/mall/goods/FS5605/info/FS5605鼻毛修剪器790 (8)_1662357072573.jpg\" /><img src=\"https://pic.flyco.net.cn/mall/goods/FS5605/info/FS5605鼻毛修剪器790 (9)_1662357074214.jpg\" /><img src=\"https://pic.flyco.net.cn/mall/goods/FS5605/info/FS5605鼻毛修剪器790 (10)_1662357075496.jpg\" /><img src=\"https://pic.flyco.net.cn/mall/goods/FS5605/info/FS5605鼻毛修剪器790 (11)_1662357078144.jpg\" /><img src=\"https://pic.flyco.net.cn/mall/goods/FS5605/info/FS5605鼻毛修剪器790 (12)_1662357079297.jpg\" /><img src=\"https://pic.flyco.net.cn/mall/goods/FS5605/info/FS5605鼻毛修剪器790 (13)_1662357080988.jpg\" /><img src=\"https://pic.flyco.net.cn/mall/goods/FS5605/info/FS5605鼻毛修剪器790 (14)_1662357083495.jpg\" /><img src=\"https://pic.flyco.net.cn/mall/goods/FS5605/info/FS5605鼻毛修剪器790 (15)_1662357087563.jpg\" /><img src=\"https://pic.flyco.net.cn/mall/goods/FS5605/info/FS5605鼻毛修剪器790 (16)_1662357088755.jpg\" /><img src=\"https://pic.flyco.net.cn/mall/goods/FS5605/info/FS5605鼻毛修剪器790 (17)_1662357092225.jpg\" />",
          "detailMobileHtml": "<img src=\"https://pic.flyco.net.cn/mall/goods/FS5605/info/FS5605鼻毛修剪器790 (1)_1662357061635.jpg\" /><img src=\"https://pic.flyco.net.cn/mall/goods/FS5605/info/FS5605鼻毛修剪器790 (2)_1662357061787.jpg\" /><img src=\"https://pic.flyco.net.cn/mall/goods/FS5605/info/FS5605鼻毛修剪器790 (3)_1662357063499.jpg\" /><img src=\"https://pic.flyco.net.cn/mall/goods/FS5605/info/FS5605鼻毛修剪器790 (4)_1662357063948.jpg\" /><img src=\"https://pic.flyco.net.cn/mall/goods/FS5605/info/FS5605鼻毛修剪器790 (5)_1662357066471.jpg\" /><img src=\"https://pic.flyco.net.cn/mall/goods/FS5605/info/FS5605鼻毛修剪器790 (6)_1662357068148.jpg\" /><img src=\"https://pic.flyco.net.cn/mall/goods/FS5605/info/FS5605鼻毛修剪器790 (7)_1662357071397.jpg\" /><img src=\"https://pic.flyco.net.cn/mall/goods/FS5605/info/FS5605鼻毛修剪器790 (8)_1662357072573.jpg\" /><img src=\"https://pic.flyco.net.cn/mall/goods/FS5605/info/FS5605鼻毛修剪器790 (9)_1662357074214.jpg\" /><img src=\"https://pic.flyco.net.cn/mall/goods/FS5605/info/FS5605鼻毛修剪器790 (10)_1662357075496.jpg\" /><img src=\"https://pic.flyco.net.cn/mall/goods/FS5605/info/FS5605鼻毛修剪器790 (11)_1662357078144.jpg\" /><img src=\"https://pic.flyco.net.cn/mall/goods/FS5605/info/FS5605鼻毛修剪器790 (12)_1662357079297.jpg\" /><img src=\"https://pic.flyco.net.cn/mall/goods/FS5605/info/FS5605鼻毛修剪器790 (13)_1662357080988.jpg\" /><img src=\"https://pic.flyco.net.cn/mall/goods/FS5605/info/FS5605鼻毛修剪器790 (14)_1662357083495.jpg\" /><img src=\"https://pic.flyco.net.cn/mall/goods/FS5605/info/FS5605鼻毛修剪器790 (15)_1662357087563.jpg\" /><img src=\"https://pic.flyco.net.cn/mall/goods/FS5605/info/FS5605鼻毛修剪器790 (16)_1662357088755.jpg\" /><img src=\"https://pic.flyco.net.cn/mall/goods/FS5605/info/FS5605鼻毛修剪器790 (17)_1662357092225.jpg\" />"
        }
      },
      {
        "product": {
          "id": 2567,
          "partnerId": 0,
          "brandId": 1,
          "productCategoryId": 3,
          "productAttributeCategoryId": 12,
          "name": "飞科鼻毛修剪器FS5601",
          "pic": "https://pic.flyco.net.cn/mall/goods/FS5601/main/FS5601-白底图2_1663901609918.jpg",
          "picWap": "https://pic.flyco.net.cn/mall/goods/FS5601/main/FS601-透明图_1663901613505.png",
          "productSn": "FS5601",
          "newStatus": "0",
          "recommandStatus": "0",
          "hotStatus": "0",
          "sort": 0,
          "sale": 0,
          "price": 69,
          "promotionPrice": 69,
          "subTitle": "飞科鼻毛修剪器男女用鼻毛剪鼻孔清洁器电动修剃鼻毛修剪刀充电式",
          "description": "立体拱形刀头 修剪探照灯",
          "unit": "",
          "weight": 0,
          "previewStatus": "0",
          "serviceIds": "",
          "keywords": "",
          "note": "",
          "detailTitle": "",
          "brandName": "飞科",
          "productCategoryName": "鼻毛修剪器",
          "spu": "",
          "color": "蓝色",
          "createTime": "2022-09-23 10:53:10",
          "albumPics": "",
          "detailDesc": "",
          "detailHtml": "<img src=\"https://pic.flyco.net.cn/mall/goods/FS5601/info/02_1663901550511.jpg\" /><img src=\"https://pic.flyco.net.cn/mall/goods/FS5601/info/03_1663901552899.jpg\" /><img src=\"https://pic.flyco.net.cn/mall/goods/FS5601/info/04_1663901554347.jpg\" /><img src=\"https://pic.flyco.net.cn/mall/goods/FS5601/info/05_1663901556530.jpg\" /><img src=\"https://pic.flyco.net.cn/mall/goods/FS5601/info/06_1663901559388.jpg\" /><img src=\"https://pic.flyco.net.cn/mall/goods/FS5601/info/07_1663901562674.jpg\" /><img src=\"https://pic.flyco.net.cn/mall/goods/FS5601/info/08_1663901565441.jpg\" /><img src=\"https://pic.flyco.net.cn/mall/goods/FS5601/info/09_1663901569691.jpg\" /><img src=\"https://pic.flyco.net.cn/mall/goods/FS5601/info/10_1663901572564.jpg\" /><img src=\"https://pic.flyco.net.cn/mall/goods/FS5601/info/11_1663901574757.jpg\" /><img src=\"https://pic.flyco.net.cn/mall/goods/FS5601/info/12_1663901576917.jpg\" /><img src=\"https://pic.flyco.net.cn/mall/goods/FS5601/info/13_1663901579535.jpg\" /><img src=\"https://pic.flyco.net.cn/mall/goods/FS5601/info/14_1663901581572.jpg\" /><img src=\"https://pic.flyco.net.cn/mall/goods/FS5601/info/15_1663901583230.jpg\" /><img src=\"https://pic.flyco.net.cn/mall/goods/FS5601/info/16_1663901585374.jpg\" />",
          "detailMobileHtml": "<img src=\"https://pic.flyco.net.cn/mall/goods/FS5601/info/02_1663901550511.jpg\" /><img src=\"https://pic.flyco.net.cn/mall/goods/FS5601/info/03_1663901552899.jpg\" /><img src=\"https://pic.flyco.net.cn/mall/goods/FS5601/info/04_1663901554347.jpg\" /><img src=\"https://pic.flyco.net.cn/mall/goods/FS5601/info/05_1663901556530.jpg\" /><img src=\"https://pic.flyco.net.cn/mall/goods/FS5601/info/06_1663901559388.jpg\" /><img src=\"https://pic.flyco.net.cn/mall/goods/FS5601/info/07_1663901562674.jpg\" /><img src=\"https://pic.flyco.net.cn/mall/goods/FS5601/info/08_1663901565441.jpg\" /><img src=\"https://pic.flyco.net.cn/mall/goods/FS5601/info/09_1663901569691.jpg\" /><img src=\"https://pic.flyco.net.cn/mall/goods/FS5601/info/10_1663901572564.jpg\" /><img src=\"https://pic.flyco.net.cn/mall/goods/FS5601/info/11_1663901574757.jpg\" /><img src=\"https://pic.flyco.net.cn/mall/goods/FS5601/info/12_1663901576917.jpg\" /><img src=\"https://pic.flyco.net.cn/mall/goods/FS5601/info/13_1663901579535.jpg\" /><img src=\"https://pic.flyco.net.cn/mall/goods/FS5601/info/14_1663901581572.jpg\" /><img src=\"https://pic.flyco.net.cn/mall/goods/FS5601/info/15_1663901583230.jpg\" /><img src=\"https://pic.flyco.net.cn/mall/goods/FS5601/info/16_1663901585374.jpg\" />"
        }
      },
      {
        "product": {
          "id": 2160,
          "partnerId": 0,
          "brandId": 1,
          "productCategoryId": 3,
          "productAttributeCategoryId": 12,
          "name": "飞科鼻毛修剪器FS5600",
          "pic": "https://pic.flyco.net.cn/mall/goods/FS5600/main/主图2_1633790357178.jpg",
          "picWap": "https://pic.flyco.net.cn/mall/goods/FS5600/main/FS5600_1663898442780.png",
          "productSn": "FS5600",
          "newStatus": "0",
          "recommandStatus": "0",
          "hotStatus": "0",
          "sort": 0,
          "sale": 0,
          "price": 69,
          "promotionPrice": 69,
          "subTitle": "飞科鼻毛修剪器男女用鼻毛剪鼻孔清洁器电动修剃鼻毛修剪刀充电式",
          "description": "立体拱形刀头 修剪探照灯",
          "unit": "",
          "weight": 0,
          "previewStatus": "0",
          "serviceIds": "",
          "keywords": "",
          "note": "",
          "detailTitle": "",
          "brandName": "飞科",
          "productCategoryName": "鼻毛修剪器",
          "spu": "",
          "color": "黑色",
          "createTime": "2021-10-09 22:31:39",
          "albumPics": "",
          "detailDesc": "",
          "detailHtml": "<img src=\"https://pic.flyco.net.cn/mall/goods/FS5600/info/宝贝详情图1_1633789841367.jpg\" /><img src=\"https://pic.flyco.net.cn/mall/goods/FS5600/info/宝贝详情图2_1633789843040.jpg\" /><img src=\"https://pic.flyco.net.cn/mall/goods/FS5600/info/宝贝详情图3_1633789843608.jpg\" /><img src=\"https://pic.flyco.net.cn/mall/goods/FS5600/info/宝贝详情图4_1633789844888.jpg\" /><img src=\"https://pic.flyco.net.cn/mall/goods/FS5600/info/宝贝详情图5_1633789845503.jpg\" /><img src=\"https://pic.flyco.net.cn/mall/goods/FS5600/info/宝贝详情图6_1633789846774.jpg\" /><img src=\"https://pic.flyco.net.cn/mall/goods/FS5600/info/宝贝详情图7_1633789847585.jpg\" /><img src=\"https://pic.flyco.net.cn/mall/goods/FS5600/info/宝贝详情图8_1633789848845.jpg\" /><img src=\"https://pic.flyco.net.cn/mall/goods/FS5600/info/宝贝详情图9_1633789849175.jpg\" /><img src=\"https://pic.flyco.net.cn/mall/goods/FS5600/info/宝贝详情图10_1633789850506.jpg\" /><img src=\"https://pic.flyco.net.cn/mall/goods/FS5600/info/宝贝详情图11_1633789850586.jpg\" /><img src=\"https://pic.flyco.net.cn/mall/goods/FS5600/info/宝贝详情图12_1633789851945.jpg\" /><img src=\"https://pic.flyco.net.cn/mall/goods/FS5600/info/宝贝详情图13_1633789852754.jpg\" /><img src=\"https://pic.flyco.net.cn/mall/goods/FS5600/info/宝贝详情图14_1633789854002.jpg\" /><img src=\"https://pic.flyco.net.cn/mall/goods/FS5600/info/宝贝详情图15_1633789854061.jpg\" /><img src=\"https://pic.flyco.net.cn/mall/goods/FS5600/info/宝贝详情图16_1633789855102.jpg\" /><img src=\"https://pic.flyco.net.cn/mall/goods/FS5600/info/宝贝详情图17_1633789856131.jpg\" /><img src=\"https://pic.flyco.net.cn/mall/goods/FS5600/info/宝贝详情图18_1633789857014.jpg\" /><img src=\"https://pic.flyco.net.cn/mall/goods/FS5600/info/宝贝详情图19_1633789857313.jpg\" /><img src=\"https://pic.flyco.net.cn/mall/goods/FS5600/info/宝贝详情图20_1633789858568.jpg\" /><img src=\"https://pic.flyco.net.cn/mall/goods/FS5600/info/宝贝详情图21_1633789858909.jpg\" /><img src=\"https://pic.flyco.net.cn/mall/goods/FS5600/info/宝贝详情图22_1633789859671.jpg\" /><img src=\"https://pic.flyco.net.cn/mall/goods/FS5600/info/宝贝详情图23_1633789859998.jpg\" /><img src=\"https://pic.flyco.net.cn/mall/goods/FS5600/info/宝贝详情图24_1633789860826.jpg\" /><img src=\"https://pic.flyco.net.cn/mall/goods/FS5600/info/宝贝详情图25_1633789861411.jpg\" /><img src=\"https://pic.flyco.net.cn/mall/goods/FS5600/info/宝贝详情图26_1633789863218.jpg\" />",
          "detailMobileHtml": "<img src=\"https://pic.flyco.net.cn/mall/goods/FS5600/info/宝贝详情图1_1633789841367.jpg\" /><img src=\"https://pic.flyco.net.cn/mall/goods/FS5600/info/宝贝详情图2_1633789843040.jpg\" /><img src=\"https://pic.flyco.net.cn/mall/goods/FS5600/info/宝贝详情图3_1633789843608.jpg\" /><img src=\"https://pic.flyco.net.cn/mall/goods/FS5600/info/宝贝详情图4_1633789844888.jpg\" /><img src=\"https://pic.flyco.net.cn/mall/goods/FS5600/info/宝贝详情图5_1633789845503.jpg\" /><img src=\"https://pic.flyco.net.cn/mall/goods/FS5600/info/宝贝详情图6_1633789846774.jpg\" /><img src=\"https://pic.flyco.net.cn/mall/goods/FS5600/info/宝贝详情图7_1633789847585.jpg\" /><img src=\"https://pic.flyco.net.cn/mall/goods/FS5600/info/宝贝详情图8_1633789848845.jpg\" /><img src=\"https://pic.flyco.net.cn/mall/goods/FS5600/info/宝贝详情图9_1633789849175.jpg\" /><img src=\"https://pic.flyco.net.cn/mall/goods/FS5600/info/宝贝详情图10_1633789850506.jpg\" /><img src=\"https://pic.flyco.net.cn/mall/goods/FS5600/info/宝贝详情图11_1633789850586.jpg\" /><img src=\"https://pic.flyco.net.cn/mall/goods/FS5600/info/宝贝详情图12_1633789851945.jpg\" /><img src=\"https://pic.flyco.net.cn/mall/goods/FS5600/info/宝贝详情图13_1633789852754.jpg\" /><img src=\"https://pic.flyco.net.cn/mall/goods/FS5600/info/宝贝详情图14_1633789854002.jpg\" /><img src=\"https://pic.flyco.net.cn/mall/goods/FS5600/info/宝贝详情图15_1633789854061.jpg\" /><img src=\"https://pic.flyco.net.cn/mall/goods/FS5600/info/宝贝详情图16_1633789855102.jpg\" /><img src=\"https://pic.flyco.net.cn/mall/goods/FS5600/info/宝贝详情图17_1633789856131.jpg\" /><img src=\"https://pic.flyco.net.cn/mall/goods/FS5600/info/宝贝详情图18_1633789857014.jpg\" /><img src=\"https://pic.flyco.net.cn/mall/goods/FS5600/info/宝贝详情图19_1633789857313.jpg\" /><img src=\"https://pic.flyco.net.cn/mall/goods/FS5600/info/宝贝详情图20_1633789858568.jpg\" /><img src=\"https://pic.flyco.net.cn/mall/goods/FS5600/info/宝贝详情图21_1633789858909.jpg\" /><img src=\"https://pic.flyco.net.cn/mall/goods/FS5600/info/宝贝详情图22_1633789859671.jpg\" /><img src=\"https://pic.flyco.net.cn/mall/goods/FS5600/info/宝贝详情图23_1633789859998.jpg\" /><img src=\"https://pic.flyco.net.cn/mall/goods/FS5600/info/宝贝详情图24_1633789860826.jpg\" /><img src=\"https://pic.flyco.net.cn/mall/goods/FS5600/info/宝贝详情图25_1633789861411.jpg\" /><img src=\"https://pic.flyco.net.cn/mall/goods/FS5600/info/宝贝详情图26_1633789863218.jpg\" />"
        }
      }
    ]
  }
}